{
    "date": "2022-05-29",
    "news_id": 130,
    "title": "國民黨「主動投案」聲援郭彥均!凌濤:說出父母憂慮錯了?",
    "article": "藝人郭彥均因在臉書分享和醫護朋友對話,其中一句「很多孩子就這樣走了」,引發爭議,行政院長蘇貞昌表示,會對網路上不實疫情訊息加以究責查辦。對此,國民黨黨主席朱立倫號召全國黨公職共同聲援郭彥均,國民黨新生代率先大串聯,台北市議員參選人柳采葳、詹為元、桃園市議員參選人凌濤、新北市議員參選人呂家愷、林鼎超等人,今(29)日由律師簡榮宗陪同,赴刑事局「主動投案」,並現場遞交投案書給警方。針對蘇貞昌稱「將加以究責查辦假訊息」,凌濤質疑,現在在台灣染疫會致命,大人講真話會被抓起來,他認為,蘇貞昌不去查打壓民眾的塔綠班,卻回過頭要查辦說出真相的民眾,「這是什麼樣的邏輯?我想問問蘇貞昌院長、陳時中指揮官,10個小朋友生命到底算多還是算少?也許在高官裡只是小數點,但對每一個父母都是百分百。」凌濤表示,自己是一個有4歲女兒的爸爸,他認為,現在全台灣父母都在憂心,小孩施打疫苗後的副作用和狀況,還有兒童快篩問題,以及孩子重症就醫完全沒有配套方案,他直言,已經讓全台灣孩子陷入非常恐慌,「身為孩子的父母,很多孩子走了是事實,大家說出父母心中的憂慮,哪一點錯了?蘇貞昌院長不去查網軍,查講出真相的人,到底在幹什麼?」他向蘇貞昌呼籲,不要再恐嚇台灣人民,要恐嚇的話所有民眾都不會接受。簡榮宗律師則指出,不論是傳染病防治法或是COVID-19特別條例,都要求是散佈謠言或是傳播不實事項才會受罰,「我們都知道郭彥均只是轉達朋友看法,還有父母的憂心。」他強調,郭彥均若被移送法辦,會無償當對方的義務律師,捍衛小朋友和父母的權益。",
    "opinions": "[{'person': '蘇貞昌', 'verb': '表示', 'opinion': '會對網路上不實疫情訊息加以究責查辦。', 'order': 0, 'negative_score': 1, 'positive_score': 0, 'negative_list': ['不實'], 'positive_list': []}, {'person': '凌濤', 'verb': '質疑', 'opinion': '現在在台灣染疫會致命,大人講真話會被抓起來,他認為,蘇貞昌不去查打壓民眾的塔綠班,卻回過頭要查辦說出真相的民眾,「這是什麼樣的邏輯?我想問問蘇貞昌院長、陳時中指揮官,10個小朋友生命到底算多還是算少?也許在高官裡只是小數點,但對每一個父母都是百分百。」', 'order': 1, 'negative_score': 2, 'positive_score': 1, 'negative_list': ['致命', '打壓'], 'positive_list': ['邏輯']}, {'person': '郭彥', 'verb': '強調', 'opinion': '郭彥均若被移送法辦,會無償當對方的義務律師,捍衛小朋友和父母的權益。', 'order': 3, 'negative_score': 0, 'positive_score': 2, 'negative_list': [], 'positive_list': ['義務', '權益']}]",
    "little_topic": "0"
}