{
    "date": "2022-05-29",
    "news_id": 133,
    "title": "徐巧芯違停!周玉蔻驚爆有內幕:明明是老公,非要說是助理",
    "article": "國民黨台北市議員徐巧芯紅線違停風波,隨著密錄器影像曝光,引發外界更多討論,其中資深媒體人周玉蔻數度發文指控徐巧芯施壓,今(29日)她持續發文,表示「明明是『老公』,非要說是『助理』!有什麼鬼詭?」,並預告明(30日)將會在自己的節目解答。周玉蔻一早的發文,很快就引來大批網友的關注,不少人留言表達看法「要『公私』分明,才能不顯出『女強』的角色」、「習慣性的說謊議員」、「真那麼差嗎?不能叫老公」、「白天是助理,晚上才叫老公」、「因為有領助理薪水吧」,其中「鄉民女神qn」黃瓊慧也現身回應「謝謝蔻姐為基層員警發聲追真相」。事實上,違停事件曝光後,徐巧芯都說當天是和男駕駛在餐廳用餐,始終對「男駕駛」身份有所保留,昨(28日)記者會上,她則是親口談「先生」,「我走出來的時候,看到他(員警)正在看我先生的身分證,上面配偶欄有我的名字,所以我就覺得大概知道我是誰,所以我出去時就習慣性自我介紹」,至於先生的身分很快被起底,名叫劉彥澧。",
    "opinions": "[{'person': '徐巧芯', 'verb': '說', 'opinion': '當天是和男駕駛在餐廳用餐,始終對「男駕駛」身份有所保留,昨(28日)記者會上,她則是親口談「先生」,「我走出來的時候,看到他(員警)正在看我先生的身分證,上面配偶欄有我的名字,所以我就覺得大概知道我是誰,所以我出去時就習慣性自我介紹」,至於先生的身分很快被起底,名叫劉彥澧。', 'order': 1, 'negative_score': 1, 'positive_score': 2, 'negative_list': ['自我'], 'positive_list': ['知道', '習慣']}]",
    "little_topic": "0"
}