{
    "date": "2022-06-05",
    "news_id": 3,
    "title": "不甩恩恩爸神隱?侯友宜:盡全力給予恩恩爸媽關懷及給資料",
    "article": "【6/0515:26發稿|18:33更新:新增影音】新北市2歲男童恩恩染疫離世後,家屬質疑因延誤就醫導致憾事,恩恩爸爸要求新北市府提供錄音,但新北市長侯友宜卻都沒有出面說明,遭質疑神隱,對此,行政院長蘇貞昌今(5)日回應時表示,此事讓人深感遺憾和痛苦,同時喊話新北市盡速給恩恩爸媽需要的資料。對此,侯友宜表示,新北市對於恩恩爸爸跟媽媽一家人會盡全力給予關懷,並按照相關規定提供資料給恩恩爸爸。至於外面聲音,大家都是好意,都是全力關懷恩恩爸爸。新北2歲童恩恩染疫病逝,恩恩父親為求真相,欲向新北市府尋求「消失的81分鐘通聯記錄」,惟新北市府至今未全力協助,更拒讓其將音檔帶回家惹議。民進黨副秘書長林鶴明並質疑,恩恩爸淚崩令人不捨,新北市長侯友宜卻神隱爽過端午?蘇貞昌上午也表示,此事讓人深感遺憾和痛苦,同時喊話新北市盡速給恩恩爸媽需要的資料。新北市下午舉行防疫記者會,媒體詢及,侯友宜遭質疑神隱過端午,上午蘇貞昌回應恩恩爸事件,他說深感遺憾和痛苦,似乎向您喊話趕快提供父母相關的資料,會不會覺得成為眾矢之的?對此,侯友宜表示,新北市對恩恩爸爸跟媽媽一家人會盡全力給予關懷,並按照相關規定提供資料給恩恩爸爸,尤其希望由衛生局消防局兩局局長,當面跟恩恩爸爸做來龍去脈說明,讓恩恩爸爸了解。至於遭批神隱,侯友宜表示,外面聲音,大家都是好意,都是全力關懷恩恩爸爸。",
    "opinions": "[{'person': '恩恩', 'verb': '質疑', 'opinion': '因延誤就醫導致憾事,恩恩爸爸要求新北市府提供錄音,但新北市長侯友宜卻都沒有出面說明,遭質疑神隱,對此,行政院長蘇貞昌今(5)日回應時表示,此事讓人深感遺憾和痛苦,同時喊話新北市盡速給恩恩爸媽需要的資料。', 'order': 0, 'negative_score': 9, 'positive_score': 2, 'negative_list': ['沒有', '延誤', '要求', '痛苦', '質疑', '遺憾', '沒有', '痛苦', '遺憾'], 'positive_list': ['說明', '求新']}, {'person': '侯友宜', 'verb': '表示', 'opinion': '新北市對於恩恩爸爸跟媽媽一家人會盡全力給予關懷,並按照相關規定提供資料給恩恩爸爸。', 'order': 1, 'negative_score': 0, 'positive_score': 3, 'negative_list': [], 'positive_list': ['全力', '給予', '關懷']}, {'person': '侯友宜', 'verb': '表示', 'opinion': '外面聲音,大家都是好意,都是全力關懷恩恩爸爸。', 'order': 4, 'negative_score': 0, 'positive_score': 4, 'negative_list': [], 'positive_list': ['全力', '好意', '好意', '關懷']}]",
    "little_topic": "0"
}