{
    "date": "2022-06-07",
    "news_id": 109,
    "title": "我F-16A迫降夏威夷 台美軍事交流再曝光!",
    "article": "我國一架F16A戰機從美國亞利桑那州的路克基地出發,回台進行升級為F-16V的構改途中,降落夏威夷檀香山機場時,因為鼻輪故障無法彈出,只能迫降,再度讓台美軍事交流曝光,前空軍副司令張延廷指出,這次故障是輕度,維修費用不會太高,美方有足夠零件處理。只是再度讓台美軍事交流曝光。網友拍下的影片中,F-16戰機的機鼻朝前,倒在跑道上,這裡是夏威夷檀香山國際機場,戰機是從美國亞利桑那州返台的我國F16A戰機,在它降落美軍希肯基地,準備進行整補時,鼻輪故障無法放出,單靠主輪降落,搭配以尾鉤拉住攔截鋼索,迫降收場。空軍司令部政戰副主任高士恒說,「我們空軍現在沒有被授權,目前沒有要評論。」前空軍副司令張延廷表示,「鼻輪放不出來,卡在裡面,只能鼻輪收上落地,那鼻輪收上落地,要把油耗光,這時候飛機最輕,進場速度跟落地速度最小,對機鼻也就是雷達部分,在跑道上的磨耗會產生最小損傷。」這架F16A從亞歷桑那州的路克基地起飛,要飛回台灣,到台中翰翔公司進行F-16升級構改工程,跨越太平洋必須停留夏威夷、關島等地,並進行多次空中加油。張延廷指出,戰機是由美軍教官駕駛,這次故障屬於輕損,費用不會太高,應該是美方負責,路克基地是我國飛官在美訓練的重要據點,除了飛行訓練之外,也包含準備維修零件、空中加油等課目,台灣飛官甚至拿過打靶比賽冠軍。以往都在檯面下低調進行,因為美中抗爭,加速台美友好,美方甚至刻意釋出訊息,美國在台協會就曾貼出我軍F-16的空中加油照片,外交部長吳釗燮也曾貼出到此一遊的留影照,一切盡在不言中!前空軍副司令張延廷表示,「那個地方比較靠近沙漠,靠近沙漠天氣非常棒,每天能見度10公里以上,而且空域非常廣泛,旁邊有設飛行炸射場,換句話說,對空、對地炸射都有設施,那就最好不過;軍事交流是其次,我認為有些政治象徵意義。大家心知肚明、不言可喻。」張延廷認為,台美軍事交流行之有年,這次意外曝光並非壞事,反而具有一定的政治上象徵意義。",
    "opinions": "[{'person': '張延廷', 'verb': '指出', 'opinion': '這次故障是輕度,維修費用不會太高,美方有足夠零件處理。', 'order': 0, 'negative_score': 3, 'positive_score': 1, 'negative_list': ['不會', '故障', '不會'], 'positive_list': ['足夠']}, {'person': '張延廷', 'verb': '表示', 'opinion': '「鼻輪放不出來,卡在裡面,只能鼻輪收上落地,那鼻輪收上落地,要把油耗光,這時候飛機最輕,進場速度跟落地速度最小,對機鼻也就是雷達部分,在跑道上的磨耗會產生最小損傷。」', 'order': 2, 'negative_score': 2, 'positive_score': 0, 'negative_list': ['損傷', '不出'], 'positive_list': []}, {'person': '張延廷', 'verb': '認為', 'opinion': '台美軍事交流行之有年,這次意外曝光並非壞事,反而具有一定的政治上象徵意義。', 'order': 5, 'negative_score': 2, 'positive_score': 1, 'negative_list': ['意外', '壞事'], 'positive_list': ['流行']}, {'person': '高士恒', 'verb': '說', 'opinion': '「我們空軍現在沒有被授權,目前沒有要評論。」', 'order': 1, 'negative_score': 2, 'positive_score': 0, 'negative_list': ['沒有', '沒有'], 'positive_list': []}]",
    "little_topic": "-1"
}