{
    "date": "2022-06-10",
    "news_id": 158,
    "title": "快篩貼盧秀燕貼紙再惹議 中市府駁斥「誤傳」絕無員工加班",
    "article": "台中市政府贈送快篩劑貼上市長盧秀燕貼紙惹議,外界傳出市府員工為此加班,綠營更點出市府在疫情高原期不拚防疫、只顧宣傳,要求盡速發放快篩試劑。市府10日否認並開放包裝現場,證實這些指控都是誤傳。新聞局長鄭照新也說,沒有加班情況,請勿以訛傳訛,惡意散佈將追究法律責任。台中市政府贈送快篩劑貼市長盧秀燕貼紙,引發議論。前立委陳柏惟7日爆料稱,秘書處叫司機和行政助理加班貼貼紙,「很落伍!」記者9日直擊發現,秘書處仍動員大量市府人力貼貼紙,秘書處否認加班,不影響同仁工作,表示「可節省經費」,2日內就可結束。台中市議會民進黨團今天上午也召開記者會表示,市府利用基層員工上班時間貼貼紙抱怨頻頻,更點出除了市府會議室外,環保局地下室、神岡國小大禮堂也都是貼貼紙的工廠。團批評,中部疫情高原期不拚防疫、只顧宣傳、累死基層,要求盧市府放棄貼紙、放過員工,盡速發放快篩試劑。台中市政府今天上午特別開放惠中樓會議室給媒體拍攝,證實現場僅是分裝,並沒有貼貼紙。另外,現場也進駐許多志工協助,部分是市府基層員工,但絕無加班或影響原本的工作。針對外界質疑台中疫情嚴峻,市府動員秘書處人力分裝快篩試劑,會影響防疫工作。秘書處副處長李政峯說明,從6月6日開始,約有20名秘書處同仁先進行篩劑分裝試裝工作,確定整個分裝流程順暢,同仁皆在工作之餘的空檔協助分裝作業,不會影響正常工作,也不會讓同仁過勞加班;後來陸陸續續投入約40名志工輪班協助,其中還有80多歲的志工也遠從豐原而來,市府非常感謝他們為防疫盡一份心。李政峯說,秘書處同仁無論是環境清消、防疫作為皆持續進行,目前是台中疫情高原期,以關心民眾健康為要,考量試劑分裝作業交給一般廠商做,會增加很多經費,因此投入市府人力分裝試劑供市民使用。分裝作業規劃5人一組,將試劑分裝為一份2劑,並貼上帶有市府關懷的貼紙,證明試劑並非來路不明,讓收到的市民安心使用;目前已分裝約14萬份,陸續志工投入會增加更多量能,只要衛生局到貨,秘書處即可進行分裝及包裝協助,以備未來「溫暖助防疫」如再進入下一階段時,能讓發放對象快速拿到試劑。新聞局長鄭照新表示,防疫期間,市府同仁都處於備戰狀態,要一起打贏防疫戰爭,同仁們都很辛苦,每次碰到防疫緊急應變時,都以防疫為優先,常會面臨工作任務調配,市府努力在同仁的辛苦與防疫工作取得平衡,很感謝所有基層公務同仁一起為防疫努力。他說,對於外界誤傳有加班情況,並沒有這樣的情況。市府庫存的快篩試劑由秘書處部分臨時人員及志工朋友協助分裝,分裝作業分為上午班(上午8時30分至12時)及下午班(下午1時至5時),中午休息的1小時和下午5時後停止作業時間,都會將倉庫閉門上鎖,以便管理快篩試劑,均有監視器紀錄佐證,並無加班情形,請勿以訛傳訛,再有惡意散佈者將追究法律責任。鄭照新說,台中市正處於防疫高原期,需要思考的是如何降低確診數,而不是為了快篩試劑裝配流程,或在有盧市長關心字樣的貼紙進行過多討論,這些對於防疫第一線人員的士氣,都是不必要的打擊;他強調,無論在高雄、桃園等其他直轄市或縣市,快篩試劑貼上帶有市長名稱的貼紙是正常的,因為市長就是市府的代言人,貼上貼紙除了表達市府的關懷,也能讓拿到試劑的市民知道通路值得信賴,代表市府認證,萬一試劑有使用上的疑慮,都可以追本溯源得到解決。",
    "opinions": "[{'person': '鄭照新', 'verb': '表示', 'opinion': '防疫期間,市府同仁都處於備戰狀態,要一起打贏防疫戰爭,同仁們都很辛苦,每次碰到防疫緊急應變時,都以防疫為優先,常會面臨工作任務調配,市府努力在同仁的辛苦與防疫工作取得平衡,很感謝所有基層公務同仁一起為防疫努力。', 'order': 4, 'negative_score': 3, 'positive_score': 5, 'negative_list': ['辛苦', '緊急', '戰爭'], 'positive_list': ['平衡', '努力', '感謝', '平衡', '感謝']}, {'person': '民進黨', 'verb': '表示', 'opinion': '市府利用基層員工上班時間貼貼紙抱怨頻頻,更點出除了市府會議室外,環保局地下室、神岡國小大禮堂也都是貼貼紙的工廠。', 'order': 1, 'negative_score': 3, 'positive_score': 0, 'negative_list': ['抱怨', '利用', '抱怨'], 'positive_list': []}, {'person': '環保局', 'verb': '批評', 'opinion': '中部疫情高原期不拚防疫、只顧宣傳、累死基層,要求盧市府放棄貼紙、放過員工,盡速發放快篩試劑。', 'order': 2, 'negative_score': 2, 'positive_score': 0, 'negative_list': ['放棄', '要求'], 'positive_list': []}, {'person': '秘書處', 'verb': '說明', 'opinion': '從6月6日開始,約有20名秘書處同仁先進行篩劑分裝試裝工作,確定整個分裝流程順暢,同仁皆在工作之餘的空檔協助分裝作業,不會影響正常工作,也不會讓同仁過勞加班;後來陸陸續續投入約40名志工輪班協助,其中還有80多歲的志工也遠從豐原而來,市府非常感謝他們為防疫盡一份心。', 'order': 3, 'negative_score': 3, 'positive_score': 6, 'negative_list': ['不會', '裝作', '不會'], 'positive_list': ['正常', '協助', '進行', '感謝', '確定', '感謝']}]",
    "little_topic": "0"
}