{
    "date": "2022-06-10",
    "news_id": 188,
    "title": "朱立倫一句話顛覆習近平的定海神針?游盈隆驚:國民黨第一人",
    "article": "國民黨主席朱立倫在近日出訪美國時,提到國民黨親美不親中,更稱「九二共識是沒有共識的共識」。對此,台灣民意基金會董事長游盈隆直言,中國國家主席習近平口中的定海神針,朱立倫一句話就顛覆掉了。游盈隆在臉書表示,朱立倫這幾天在美國的言論想不讓人注意也難。他努力想撕掉中國國民黨親共的標籤,甚至想塗掉中國國民黨親中的胎記。但他做得到嗎?接受媒體訪問時,一句「國民黨從來不是一個『親中』的政黨,而是『親美』的政黨」,剎那間不知讓多少人楞在當場或昏倒在地。游盈隆認為,國民黨就算是簡稱,大家都知道指的就是「中國國民黨」。朱立倫說國民黨從來不親中而是親美,這怎麼講的通呢?不論從近百年、近70年、近30年、或近15年歷史,不論從哪個角度講,都是「高山滾鼓」,不通、不通。一句話,通通都是違反歷史的陳述。朱立倫為何如此不顧一切,就算是違反一般人常識也要這樣講?游盈隆提到,關於國共唱和多年的九二共識,習近平口中的定海神針,朱立倫一句「九二共識是沒有共識的共識」,就顛覆掉了。這個說法,坦白講比較接近1992年兩岸兩會香港會談的歷史事實。2016年5月20日,總統蔡英文在總統就職演說中絕口不提「九二共識」,時間一晃6年,定海神針不見了,台海和平穩定依舊,沒有地動山搖。游盈隆認為,終結九二共識之亂,蔡英文功不可沒,歷史會記上一筆。此次,朱立倫以現任國民黨主席身份再補一槍,無疑是國民黨史上第一人,也可歷史留名,但黨內要找他算帳的人已經大排長龍,長過排快篩劑。游盈隆也提到,朱立倫提Pro-China或Pro-USA這個立論背後的問題意識,頗堪玩味。親中或親美?只有在美中戰爭、鬥爭或競爭中,面臨選邊時才會有這個問題出現,而且必須自身先否定自己具有「中華民國/中國」的身分時,講這個話才有意義。換句話說,除非在他心中認定「台灣=中華民國」且「中華民國不等於中國」,先去中國化,否則有什麼立場講親中或親美呢?最後,游盈隆說,朱立倫這次美國行引起的關注和爭議不小,後遺症更大,如果他的出發點是想藉此重建國民黨形象,爭取台灣社會支持,為2022選舉孤注一躑,增加大選話題和籌碼,他已踏出艱辛的第一步,雖然步伐略顯踉蹌,姿勢也不算優雅從容。",
    "opinions": "[{'person': '朱立倫', 'verb': '說', 'opinion': '法,坦白講比較接近1992年兩岸兩會香港會談的歷史事實。', 'order': 4, 'negative_score': 0, 'positive_score': 1, 'negative_list': [], 'positive_list': ['坦白']}, {'person': '朱立倫', 'verb': '提到', 'opinion': '國民黨親美不親中,更稱「九二共識是沒有共識的共識」。', 'order': 0, 'negative_score': 2, 'positive_score': 0, 'negative_list': ['沒有', '沒有'], 'positive_list': []}, {'person': '游盈隆', 'verb': '提到', 'opinion': '關於國共唱和多年的九二共識,習近平口中的定海神針,朱立倫一句「九二共識是沒有共識的共識」,就顛覆掉了。', 'order': 3, 'negative_score': 3, 'positive_score': 0, 'negative_list': ['沒有', '顛覆', '沒有'], 'positive_list': []}, {'person': '游盈隆', 'verb': '表示', 'opinion': '朱立倫這幾天在美國的言論想不讓人注意也難。', 'order': 1, 'negative_score': 0, 'positive_score': 1, 'negative_list': [], 'positive_list': ['注意']}, {'person': '蔡英文', 'verb': '說', 'opinion': '中絕口不提「九二共識」,時間一晃6年,定海神針不見了,台海和平穩定依舊,沒有地動山搖。', 'order': 5, 'negative_score': 3, 'positive_score': 3, 'negative_list': ['不見', '沒有', '沒有'], 'positive_list': ['平穩', '和平', '穩定']}]",
    "little_topic": "0"
}