{
    "date": "2022-06-02",
    "news_id": 212,
    "title": "端節前夕慰勉陸戰隊66旅 蔡英文親扛「紅隼」反裝甲火箭",
    "article": "端午連假將至,總統蔡英文(2)日特到北部地區部隊,包括海軍陸戰隊66旅與國防醫學院預防醫學研究所,頒發加菜金慰勉官兵。蔡英文在海軍陸戰隊六六旅,聽取官兵介紹所使用的武器裝備後,她還實際扛起國造紅隼反裝甲火箭模擬操作。蔡英文上午在國安會秘書長顧立雄、國防部長邱國正等人陪同下,前往海軍陸戰隊六六旅慰勉部隊,肯定官兵堅守崗位,戮力戰備整備之辛勞。六六旅陳展紅隼反裝甲火箭、標槍飛彈、雙聯裝刺針飛彈、T108輕型狙擊槍、各式夜視鏡等裝備向蔡蔡英文介紹。蔡英文在聽取官兵簡介紅隼反裝甲火箭後,仔細詢問如何操作與發射,隨後更是出乎眾人意料之外,親自提起未含實彈的火箭筒上肩,並向官兵再度仔細詢問要如何使用以及發射方式,更親自體驗操作方式。媒體詢問總統會不會覺得重?蔡英文先說「不會」,更表示「我就在試它的重量,蠻好操作的」。蔡英文接下來聽取國軍報告、操作標槍飛彈結束後,媒體喊話,「總統沒拿喔?」蔡總統說,「這21公斤ㄟ(發射筒加飛彈總重量),這裡已經有一個女生(操作女兵)拿了」。",
    "opinions": "[{'person': '蔡英文', 'verb': '說', 'opinion': '「這21公斤ㄟ(發射筒加飛彈總重量),這裡已經有一個女生(操作女兵)拿了」。', 'order': 1, 'negative_score': 0, 'positive_score': 0, 'negative_list': [], 'positive_list': []}]",
    "little_topic": "2"
}