{
    "pict_path": null,
    "opinions": [
        {
            "person": "王定宇",
            "verb": "說",
            "opinion": "今年國內疫情升溫、確診人數上升,但是中、重症的比例極低,社會在走向共存的狀態,詢問今年7月的漢光演習實兵操演,會不會因為疫情有暫緩的計畫或備案。",
            "negative_score": 2,
            "positive_score": 0,
            "negative_list": [
                "不會",
                "不會"
            ],
            "positive_list": [],
            "datetime": "2022-05-26 11:36"
        },
        {
            "person": "王定宇",
            "verb": "指出",
            "opinion": "今年5月16日到5月20日的漢光38號演習,因為俄烏戰爭調整為圖上兵推,詢問這個跟傳統兵推有什麼差別。",
            "negative_score": 2,
            "positive_score": 0,
            "negative_list": [
                "差別",
                "戰爭"
            ],
            "positive_list": [],
            "datetime": "2022-05-26 11:36"
        },
        {
            "person": "王定宇",
            "verb": "認為",
            "opinion": "疫情升溫也是操演當中的變數,遇到疫情就停下來的話,「演習視同作戰,那作戰不就停打了」,邱國正認同說,「委員講的很對」。",
            "negative_score": 2,
            "positive_score": 1,
            "negative_list": [
                "作戰",
                "不就"
            ],
            "positive_list": [
                "認同"
            ],
            "datetime": "2022-05-26 15:33"
        },
        {
            "person": "王定宇",
            "verb": "說",
            "opinion": "「他本身並無惡意也沒有被查辦,而國民黨也沒有跟郭彥均討論徵求同意,就用全黨的名義說他們大家都是郭彥均,利用了一些寶貴的生命利用悲劇,來操弄讓社會混亂,目的是為了政治不是為了人命。」",
            "negative_score": 7,
            "positive_score": 4,
            "negative_list": [
                "沒有",
                "混亂",
                "惡意",
                "悲劇",
                "不是",
                "利用",
                "沒有"
            ],
            "positive_list": [
                "同意",
                "無惡意",
                "寶貴",
                "寶貴的"
            ],
            "datetime": "2022-05-30 17:40"
        },
        {
            "person": "王定宇",
            "verb": "認為",
            "opinion": "中國麻煩製造者的行為,反而推動周邊國家團結,擴張的結果是損人不利己。",
            "negative_score": 5,
            "positive_score": 0,
            "negative_list": [
                "不利",
                "利己",
                "麻煩",
                "不利",
                "麻煩"
            ],
            "positive_list": [],
            "datetime": "2022-05-31 18:47"
        },
        {
            "person": "王定宇",
            "verb": "認為",
            "opinion": "中國麻煩製造者的行為,反而推動周邊國家團結,擴張的結果是損人不利己。",
            "negative_score": 5,
            "positive_score": 0,
            "negative_list": [
                "不利",
                "利己",
                "麻煩",
                "不利",
                "麻煩"
            ],
            "positive_list": [],
            "datetime": "2022-05-31 12:54"
        },
        {
            "person": "王定宇",
            "verb": "表示",
            "opinion": "任何一起空難都原因,對於保衛國家的年輕生命消逝,國家、家屬都感到無比心痛,每一趟任務每一次起飛都有風險,從事這份工作的人內心都知道,但心裡仍無法接受,呼籲軍方快速下令AT-3面停飛,「等到檢查完才可復飛」。",
            "negative_score": 3,
            "positive_score": 3,
            "negative_list": [
                "無法",
                "心痛",
                "無法"
            ],
            "positive_list": [
                "知道",
                "接受",
                "無比"
            ],
            "datetime": "2022-05-31 10:39"
        },
        {
            "person": "王定宇",
            "verb": "說",
            "opinion": "「我們台灣的P4實驗室,是全亞洲第2座、全世界第8座、第8國擁有,當時是經由以色列跟我們的合作,來建置起來,所以它一直是非常機密的單位。」",
            "negative_score": 0,
            "positive_score": 3,
            "negative_list": [],
            "positive_list": [
                "合作",
                "擁有",
                "合作"
            ],
            "datetime": "2022-06-02 19:37"
        },
        {
            "person": "王定宇",
            "verb": "指出",
            "opinion": "柯文哲稱他一直以為24小時內要火化,一直到前天才知道不是這樣,中國國民黨這二天也一直亂扯規定不清楚來攻擊防疫指揮中心。",
            "negative_score": 7,
            "positive_score": 3,
            "negative_list": [
                "不清",
                "不清楚",
                "攻擊",
                "不是",
                "不清",
                "攻擊",
                "亂扯"
            ],
            "positive_list": [
                "天才",
                "知道",
                "清楚"
            ],
            "datetime": "2022-06-06 11:33"
        },
        {
            "person": "王定宇",
            "verb": "批評",
            "opinion": "難得一見這麼大一隻卻沒出息的傢伙!中國媒體《觀察者網》報導,中國智庫「國際經濟交流研究中心」總經濟師陳文玲引述美國前國務卿季辛吉(HenryKissinger)日前在瑞士達佛斯世界經濟論壇上的發言,稱中美若能緩和敵對關係,對整體世界和平具有重要性。",
            "negative_score": 5,
            "positive_score": 5,
            "negative_list": [
                "傢伙",
                "敵對",
                "沒出息",
                "傢伙",
                "敵對"
            ],
            "positive_list": [
                "和平",
                "重要",
                "重要性",
                "緩和",
                "出息"
            ],
            "datetime": "2022-06-07 14:40"
        }
    ]
}