{
    "date": "2022-05-30",
    "news_id": 84,
    "title": "水曜日預告/北歐中立國模式告終:瑞典自強最前線 爆紅短影音背後:抖音的996血汗",
    "article": "社群中心/陳恩迪整理本週三(06/01)《水曜日聊世界EP.36》李慧芝和劉方慈主播將帶來全球最新熱議:「瑞典自強最前線」和「抖音的996血汗」。內容飽和、精闢討論讓您不再霧裡看花,盡在週三晚間9:10民視新聞網臉書《水曜日聊世界》線上直播!本集《水曜日聊世界EP.36》首先從「瑞典自強最前線」開始。5月18日,瑞典及芬蘭兩國,正式聯合提交加入北約的申請,預計能大幅補充北約的軍事實力。目前,瑞典與芬蘭擁有現役軍人,分別是2萬4千人和2萬3千人,且後備役兵員十分充足,尤其是芬蘭,擁有87萬至90萬後備役,全國約3分之1人口皆服過役。另外,兩國還擁有世界知名的軍工業公司,堪稱是北歐最強軍力。國人對瑞典認知多半是連鎖家具行「IKEA」,但您知道它們過去是常年的中立國嗎?在核武威脅壟罩的俄烏戰爭中,竟然有遏止這一切的控制能力?號稱「歐洲三雄」的戰鬥機其中之一竟是瑞典發明?請鎖定本週三晚間9:10的《水曜日聊世界》!《水曜日聊世界EP.36》還加入了「抖音的996血汗」話題。阿里巴巴創辦人馬雲曾提出,上班族早上9點工作到晚上9點,每周工作6天的「996加班文化」,是一種巨大的福報,認為不付出超越他人的努力和時間,如何實現成功,還表示996是他用來鼓勵阿里巴巴員工的精神,並引以為榮,馬雲一番話引發熱議,中國政府也發出聲明,指出996的工作制度違法,雖然有官方出面,但中國多數公司仍有勞動者被迫加班的情形,而備受用戶喜愛的中國短影音平台抖音和海外版TikTok,近日也傳出有美國分公司的前員工,出面控訴996加班文化,令人崩潰的消息。據《華爾街日報》爆料,996竟染指美國?抖音與TikTok究竟是什麼關係?它又是如何爆紅?光聽就很香的世界十大工時最短國家,台灣又排名第幾?無須考慮,本週三晚上9:10一同加入《水曜日聊世界》!⬇️上集《水曜日聊世界EP.35》(澳洲大選癥結點、南亞超極限熱浪)⬇️即日起,《水曜日聊世界》每週三晚上9:10在「民視新聞臉書粉絲團」跟大家雲端相見,有任何寶貴意見或想詢問主播,歡迎留言或即時討論!民視新聞最新世界話題、最強雙姝組合、嶄新直播企劃盡在《水曜日聊世界》!【直播平台】民視新聞FB粉絲團民視讚夯YT頻道【直播時間】每週三晚間9點10分【本週主題】「瑞典自強最前線」;「抖音的996血汗」。",
    "opinions": "[]",
    "little_topic": "0"
}