{
    "date": "2022-05-26",
    "news_id": 238,
    "title": "桃園市長「突襲式」提名惹議 張善政欲滅火數度訪邱奕勝「強迫達陣」",
    "article": "國民黨主席朱立倫18日突襲式徵召前行政院長張善政參選桃園市長,引爆桃園藍營地方勢力大反彈,這一周來朱立倫、張善政忙著道歉滅火。不過朱、張試圖拜訪桃園市議長邱奕勝時,卻因事先未聯繫確認即登門,數度吃了閉門羹,但張善政仍未放棄就是非要見到人,邱奕勝在壓力下,今(26)日上午利用接見訪客空檔,與張相約在桃園市議會與碰面,2人並私下會談10多分鐘,張善政終於如願「強迫」達陣成功。相較台北市議員羅智強從23日在桃園展開祈福之旅,並在中壢區設桃園疫情關懷中心,邱奕勝昨天還主動到場給羅鼓勵,與冷淡對待張善政對比十分鮮明。而今天上午張善政與羅智強一同在中壢行腳,也是張善政主動打電話給羅詢問,「可不可以陪你走一段?」羅智強並未拒絕,但強調行腳是為疫情不談選舉。羅智強、張善政在中壢街頭邊走邊聊,沿途也發送祈福茶包給店家;2人都說今天是為了解桃園市民在疫情下的困境,不會觸及選舉話題。張善政表示,今天就是來走一走,關懷一下桃園的狀況,選舉是一時的,關心桃園是永久的,與羅智強的交情也是永久的;羅智強則指出,這一路其實不管選不選舉,有沒有職務,他為桃園做事這件事是不會變的,張善政為他加油打氣,也讓他相當感動。由於羅智強先前為選桃園市長已經在龜山區買了房子,未來張善政將會桃園市何處購屋?張則說,不受限任何區域,價格大小符合即可。在結束與羅智強的行腳後,張善政隨即前往桃園市議會與邱奕勝碰面,2人互換禮物、合影表達友善,並在議長室短暫會談10多分鐘。邱奕勝解釋,張善政這幾天行程多也非常急碰面,他就把時間擠出來,剛好今天有其他客人到議長室,因此就跟張約上午見面。邱稱讚張善政是國民黨不可多得的人才,以學經歷來講是他的前輩,他非常尊敬張,也會全力支持。另外邱奕勝也強調,朱立倫擔任桃園縣長時,他是副議長,雙方互動良好沒有心結;他本身也是國民黨中常委,和張善政間也沒有外傳的心結。張善政與邱奕勝短暫會面後則表示,他與邱聊了很多層面,了解地方很多情況,雖然時間不長,但資訊都非常重要、寶貴,過一陣子他也會約更多議員交流。至於地方整合的問題,張善政說,就是一步一步走,自然都會水到渠成。他還對已表態參選,對黨中央徵召非常不滿的立委呂玉玲喊話說,他要向呂表達對她在桃園耕耘多年的敬意,也希望能徵詢她的意見,會持續的與呂玉玲聯絡,希望她方便時可以碰面。媒體也追問,邱奕勝是否有表態支持?張善政則稱,「這個不用講,一定是這樣」。",
    "opinions": "[{'person': '羅智強', 'verb': '強調', 'opinion': '行腳是為疫情不談選舉。', 'order': 0, 'negative_score': 0, 'positive_score': 0, 'negative_list': [], 'positive_list': []}, {'person': '張善政', 'verb': '說', 'opinion': '不受限任何區域,價格大小符合即可。', 'order': 3, 'negative_score': 1, 'positive_score': 1, 'negative_list': ['不受'], 'positive_list': ['符合']}, {'person': '張善政', 'verb': '說', 'opinion': '今天是為了解桃園市民在疫情下的困境,不會觸及選舉話題。', 'order': 1, 'negative_score': 4, 'positive_score': 1, 'negative_list': ['不會', '困境', '觸及', '不會'], 'positive_list': ['了解']}, {'person': '張善政', 'verb': '說', 'opinion': '就是一步一步走,自然都會水到渠成。', 'order': 7, 'negative_score': 0, 'positive_score': 1, 'negative_list': [], 'positive_list': ['自然']}, {'person': '邱奕勝', 'verb': '解釋', 'opinion': '張善政這幾天行程多也非常急碰面,他就把時間擠出來,剛好今天有其他客人到議長室,因此就跟張約上午見面。', 'order': 4, 'negative_score': 0, 'positive_score': 0, 'negative_list': [], 'positive_list': []}, {'person': '邱奕勝', 'verb': '強調', 'opinion': '朱立倫擔任桃園縣長時,他是副議長,雙方互動良好沒有心結;他本身也是國民黨中常委,和張善政間也沒有外傳的心結。', 'order': 5, 'negative_score': 2, 'positive_score': 2, 'negative_list': ['沒有', '沒有'], 'positive_list': ['良好', '良好']}, {'person': '呂玉玲', 'verb': '說', 'opinion': '他要向呂玉玲表達對她在桃園耕耘多年的敬意,也希望能徵詢她的意見,會持續的與呂玉玲聯絡,希望她方便時可以碰面。', 'order': 8, 'negative_score': 0, 'positive_score': 3, 'negative_list': [], 'positive_list': ['方便', '希望', '希望']}]",
    "little_topic": "0"
}