{
    "date": "2022-05-26",
    "news_id": 68,
    "title": "北市+9062例!中小學、公幼下週遠距 柯文哲視訊說明",
    "article": "中央流行疫情指揮中心26日公布,新增8萬1852例本土確診,另增104例死亡,個案分佈以新北市1萬7632例為最多,其次是台中市9944例、桃園市9484例、台北市9062例。針對台北市疫情現況,台北市政府下午3時30分召開防疫記者會,由《東森新媒體ETtoday》全程直播。指揮中心表示,新增8萬1852例本土病例,個案分布為新北市1萬7632例,台中市9944例,桃園市9484例,台北市9062例,高雄市8566例,台南市5871例,彰化縣3281例,屏東縣2623例,新竹縣2282例,宜蘭縣2041例,苗栗縣1700例,基隆市1690例,新竹市1679例,花蓮縣1291例,雲林縣1105例,南投縣1004例,嘉義縣920例,台東縣749例,嘉義市522例,澎湖縣206例,金門縣182例,連江縣18例。台北市政府26日下午召開防疫記者會,由於台北市長柯文哲、台北市副市長蔡炳坤確診居隔,因此採視訊參與,而確診解隔的台北市副市長黃珊珊則親自出席,將宣布北市中小學、公幼下週遠距教學、疫苗接種計畫等議題。",
    "opinions": "[{'person': '黃珊珊', 'verb': '宣布', 'opinion': '北市中小學、公幼下週遠距教學、疫苗接種計畫等議題。', 'order': 1, 'negative_score': 0, 'positive_score': 0, 'negative_list': [], 'positive_list': []}]",
    "little_topic": "4"
}