{
    "date": "2022-06-03",
    "news_id": 29,
    "title": "觀點投書:疫情下的深思",
    "article": "近日某藝人發文探討疫情時事的文馬上被各路政府炎上「傳播假消息」,這個反應速度比探討什麼時候不要再雙標對待海歸的議題研究還迅速。同時,今日(5/28)疫情指揮中心宣布的死亡人數為127;其中因這一波omicron疫情導致的幼童死亡數累積達10人。想到上一次輿論發酵,政府也炎上的假消息是「德國快篩30塊,德國人天天都要快篩才能出門」這一則真假參半的消息,其目的要掩飾的是台灣快篩不夠以外;快篩的零售價格令人存疑的事實,轉移大家(台灣本土民眾)的注意力。再想到被分化被獵巫的海歸族群是如何的被政府帶頭雙標對待兼歧視就不贅述。我覺得防疫政策在防疫上有沒有成效真的以科學說話,但是指揮中心的作法蠻印證《商君書》所提到的馭民五術來如何鞏固政權>>跟兩年多來一切防疫措施需以疫情指揮中心為準,其他地方政府百家爭鳴的作法大多數是先不接受先否決完再照抄答案。只有使人民思想單純,人民才不易反抗政府,這樣國家才會容易治理,政府的地位才會牢固。>>跟兩年多來的指揮中心沒有樹立防疫的正確觀念,境外永遠是自帶病毒般的單一思想,所以對內基本來說大家防疫有沒有落實不確定,但是能確定的是槍口一定對外要雙標標滿的防好海歸,即使國內疫情爆炸,千錯萬錯都是境外移入的錯。尤其看到兩年下來的單一思想的台灣本土民眾,大部分的人還是很恐慌國境開放的政策,想要依賴著政府繼續關國門,卻沒有思辨能力這些作法已經剝奪人權而不自知。>>從口罩到疫苗到快篩,超前部署的政策真的幫民眾尋覓很多事情可以去做呢?>>這個應該是不僅限於疫情下的政府,也涵蓋了台灣的政治鬥爭;但是近兩年來因為「疫情散播假消息」這件事會開罰;但是罰的準則卻不一定是罰真的假消息還是罰一個政府不讓說的真消息。>>同樣的防疫三寶,口罩疫苗快篩(或PCR);各國政府都有應對的措施在確實科學的防疫上;台灣也編列的防疫預算8400億卻沒人知道實際花在哪,為何疫情擴散的時候要什麼缺什麼;民眾還要花時間跟準備荷包去排隊購買防疫物資;同時也要再剝一層海歸貢獻給防疫旅館的一層民脂民膏跟自費PCR;而真正的第一線醫護人員更是吃緊人力與裝備。台灣是一個民主且法治的社會,我最不希望的是看到防疫措施用某某某官員「震怒」、「拍板」、「受惠」、「再增適用對象/擴大族群」這些等如同極權統治下的用詞,民眾如同螻蟻般要感恩戴德像是受政府的小恩小惠,但是那些措施是本來就應該實施的政策。民粹與民主僅一字之差,卻差之千里。",
    "opinions": "[{'person': '中央流行疫情指揮中心', 'verb': '宣布', 'opinion': '的死亡人數為127;其中因這一波omicron疫情導致的幼童死亡數累積達10人。', 'order': 0, 'negative_score': 1, 'positive_score': 0, 'negative_list': ['死亡'], 'positive_list': []}]",
    "little_topic": "0"
}